embeddingsprep/__init__.py
embeddingsprep/models/__init__.py
embeddingsprep/models/utils.py
embeddingsprep/models/word2vec.py
embeddingsprep/preprocessing/__init__.py
embeddingsprep/preprocessing/preprocessor.py
embeddingsprep/preprocessing/utils/__init__.py
embeddingsprep/preprocessing/utils/readers.py
embeddingsprep/preprocessing/utils/structure.py
embeddingsprep-0.1.4.dist-info/LICENSE
embeddingsprep-0.1.4.dist-info/METADATA
embeddingsprep-0.1.4.dist-info/WHEEL
embeddingsprep-0.1.4.dist-info/top_level.txt
embeddingsprep-0.1.4.dist-info/RECORD
