Metadata-Version: 2.1
Name: embeddingsprep
Version: 0.1.4
Summary: A word2vec preprocessing and training package
Home-page: https://github.com/sally14/embeddings
Author: sally14
Author-email: sally14.doe@gmail.com
License: UNKNOWN
Platform: UNKNOWN
Classifier: Programming Language :: Python :: 3
Classifier: License :: OSI Approved :: MIT License
Classifier: Operating System :: OS Independent
Requires-Python: >=3.6
Requires-Dist: docopt (>=0.6.2)
Requires-Dist: gensim (>=3.8.1)
Requires-Dist: nltk (>=3.4.5)
Requires-Dist: glob
